{"name": "Bed Town",
 "permalink": "bed-town",
 "crunchbase_url": "http://www.crunchbase.com/company/bed-town",
 "homepage_url": "http://www.bedtown.co.uk",
 "blog_url": "",
 "blog_feed_url": "",
 "twitter_username": "bedtownuk",
 "category_code": "ecommerce",
 "number_of_employees": 5,
 "founded_year": 2008,
 "founded_month": 1,
 "founded_day": 4,
 "deadpooled_year": null,
 "deadpooled_month": null,
 "deadpooled_day": null,
 "deadpooled_url": null,
 "tag_list": "leather-beds, metal-beds, mattresses, bedroom-furniture",
 "alias_list": null,
 "email_address": "sales@bedtown.co.uk",
 "phone_number": "01159702111",
 "description": "UK supplier of quality leather beds",
 "created_at": "Thu Mar 15 10:47:56 UTC 2012",
 "updated_at": "Mon Apr 23 23:11:47 UTC 2012",
 "overview": "\u003Cp\u003EOffers high quality beds at low prices, one the UKs largest retailer of beds and mattresses\u003C/p\u003E",
 "image":
  {"available_sizes":
    [[[150,
       111],
      "assets/images/resized/0018/5193/185193v2-max-150x150.png"],
     [[250,
       186],
      "assets/images/resized/0018/5193/185193v2-max-250x250.png"],
     [[255,
       190],
      "assets/images/resized/0018/5193/185193v2-max-450x450.png"]],
   "attribution": null},
 "products":
  [],
 "relationships":
  [],
 "competitions":
  [],
 "providerships":
  [],
 "total_money_raised": "$0",
 "funding_rounds":
  [],
 "investments":
  [],
 "acquisition": null,
 "acquisitions":
  [],
 "offices":
  [],
 "milestones":
  [],
 "ipo": null,
 "video_embeds":
  [],
 "screenshots":
  [],
 "external_links":
  [{"external_url": "http://www.bedtown.co.uk/leather-beds-s/1477.htm",
    "title": "Leather Beds"},
   {"external_url": "http://www.bedtown.co.uk/metal-beds-s/1513.htm",
    "title": "Metal Beds"},
   {"external_url": "http://www.bedtown.co.uk/bedroom-furniture-s/1820.htm",
    "title": "Bedroom Furniture"}]}