{"name": "Betwext",
 "permalink": "betwext",
 "crunchbase_url": "http://www.crunchbase.com/company/betwext",
 "homepage_url": "http://betwext.com",
 "blog_url": "http://betwext.com/blog",
 "blog_feed_url": "http://betwext.com/blog/feed",
 "twitter_username": "betwext",
 "category_code": "mobile",
 "number_of_employees": 3,
 "founded_year": 2010,
 "founded_month": 3,
 "founded_day": null,
 "deadpooled_year": null,
 "deadpooled_month": null,
 "deadpooled_day": null,
 "deadpooled_url": null,
 "tag_list": "sms, mobile-marketing, sms-marketing, text-marketing, sms-campaigns",
 "alias_list": null,
 "email_address": "info@betwext.com",
 "phone_number": "",
 "description": "SMS Text Marketing",
 "created_at": "Sun Feb 13 00:39:41 UTC 2011",
 "updated_at": "Thu Feb 17 03:29:05 UTC 2011",
 "overview": "\u003Cp\u003EBetwext creates and manages web-based applications centered around providing various SMS marketing services to consumers and businesses.\u003C/p\u003E\n\n\u003Cp\u003EBetwext Broadcast gives you a unique phone number and inexpensive messages - this allows your marketing efforts to go further for fewer dollars. Broadcast is designed to be a web app that\u0026#8217;s not only easy to use, but also extremely powerful.\u003C/p\u003E",
 "image":
  {"available_sizes":
    [[[146,
       42],
      "assets/images/resized/0012/1866/121866v2-max-150x150.png"],
     [[146,
       42],
      "assets/images/resized/0012/1866/121866v2-max-250x250.png"],
     [[146,
       42],
      "assets/images/resized/0012/1866/121866v2-max-450x450.png"]],
   "attribution": null},
 "products":
  [],
 "relationships":
  [{"is_past": false,
    "title": "CEO",
    "person":
     {"first_name": "Jonathan",
      "last_name": "Kressaty",
      "permalink": "jonathan-kressaty",
      "image":
       {"available_sizes":
         [[[150,
            106],
           "assets/images/resized/0012/1867/121867v2-max-150x150.jpg"],
          [[250,
            177],
           "assets/images/resized/0012/1867/121867v2-max-250x250.jpg"],
          [[450,
            319],
           "assets/images/resized/0012/1867/121867v2-max-450x450.jpg"]],
        "attribution": ""}}},
   {"is_past": false,
    "title": "COO",
    "person":
     {"first_name": "Chuck",
      "last_name": "Reynolds",
      "permalink": "chuck-reynolds",
      "image":
       {"available_sizes":
         [[[150,
            150],
           "assets/images/resized/0005/1315/51315v4-max-150x150.jpg"],
          [[250,
            250],
           "assets/images/resized/0005/1315/51315v4-max-250x250.jpg"],
          [[300,
            300],
           "assets/images/resized/0005/1315/51315v4-max-450x450.jpg"]],
        "attribution": ""}}},
   {"is_past": false,
    "title": "CEO",
    "person":
     {"first_name": "Jonathan",
      "last_name": "Kressaty",
      "permalink": "jonathan-kressaty",
      "image":
       {"available_sizes":
         [[[150,
            106],
           "assets/images/resized/0012/1867/121867v2-max-150x150.jpg"],
          [[250,
            177],
           "assets/images/resized/0012/1867/121867v2-max-250x250.jpg"],
          [[450,
            319],
           "assets/images/resized/0012/1867/121867v2-max-450x450.jpg"]],
        "attribution": ""}}}],
 "competitions":
  [],
 "providerships":
  [],
 "total_money_raised": "$0",
 "funding_rounds":
  [],
 "investments":
  [],
 "acquisition": null,
 "acquisitions":
  [],
 "offices":
  [{"description": "",
    "address1": "",
    "address2": "",
    "zip_code": "85225",
    "city": "Chandler",
    "state_code": "AZ",
    "country_code": "USA",
    "latitude": null,
    "longitude": null}],
 "milestones":
  [],
 "ipo": null,
 "video_embeds":
  [],
 "screenshots":
  [],
 "external_links":
  [{"external_url": "http://blog.twilio.com/2010/02/sms-beta-context-winner-betwext-by-jonathan-kressaty.html",
    "title": "Betwext Wins Twilio SMS Developer Contest"},
   {"external_url": "http://blog.twilio.com/2011/01/twilio-powered-betwext-keeps-700-attendees-updated-at-wordcamp-phoenix.html",
    "title": "Betwext Keeps 700+ Attendees Updated at Wordcamp Phoenix"}]}