{"name": "Biomimedica",
 "permalink": "biomimedica",
 "crunchbase_url": "http://www.crunchbase.com/company/biomimedica",
 "homepage_url": "http://www.biomimedica.com",
 "blog_url": "",
 "blog_feed_url": "",
 "twitter_username": "",
 "category_code": "biotech",
 "number_of_employees": null,
 "founded_year": null,
 "founded_month": null,
 "founded_day": null,
 "deadpooled_year": null,
 "deadpooled_month": null,
 "deadpooled_day": null,
 "deadpooled_url": null,
 "tag_list": "",
 "alias_list": "",
 "email_address": "info@biomimedica.com",
 "phone_number": "650-243-3850",
 "description": "A medical device company",
 "created_at": "Fri Jun 22 12:29:49 UTC 2012",
 "updated_at": "Fri Jun 22 12:39:38 UTC 2012",
 "overview": "\u003Cp\u003EBiomimedica is a medical device company that is pioneering new approaches to joint repair through its proprietary, synthetic cartilage technology.\u003C/p\u003E",
 "image":
  {"available_sizes":
    [[[150,
       38],
      "assets/images/resized/0019/6788/196788v1-max-150x150.jpg"],
     [[250,
       64],
      "assets/images/resized/0019/6788/196788v1-max-250x250.jpg"],
     [[374,
       96],
      "assets/images/resized/0019/6788/196788v1-max-450x450.jpg"]],
   "attribution": null},
 "products":
  [],
 "relationships":
  [],
 "competitions":
  [],
 "providerships":
  [],
 "total_money_raised": "$11.9M",
 "funding_rounds":
  [{"round_code": "b",
    "source_url": "http://www.finsmes.com/2012/06/biomimedica-closes-11-9m-series-b-financing.html?utm_source=feedburner\u0026utm_medium=feed\u0026utm_campaign=Feed%3A+finsmes%2FcNHu+%28FinSMEs%29",
    "source_description": "Biomimedica Closes $11.9M Series-B Financing",
    "raised_amount": 11900000.0,
    "raised_currency_code": "USD",
    "funded_year": 2012,
    "funded_month": 6,
    "funded_day": 22,
    "investments":
     [{"company": null,
       "financial_org":
        {"name": "Troika Ventures",
         "permalink": "troika-ventures",
         "image": null},
       "person": null},
      {"company": null,
       "financial_org":
        {"name": "Emergent Medical Partners",
         "permalink": "emergent-medical-partners",
         "image":
          {"available_sizes":
            [[[150,
               67],
              "assets/images/resized/0005/5114/55114v1-max-150x150.png"],
             [[250,
               113],
              "assets/images/resized/0005/5114/55114v1-max-250x250.png"],
             [[252,
               114],
              "assets/images/resized/0005/5114/55114v1-max-450x450.png"]],
           "attribution": null}},
       "person": null},
      {"company": null,
       "financial_org":
        {"name": "Asset Management Ventures",
         "permalink": "asset-management-ventures",
         "image":
          {"available_sizes":
            [[[150,
               11],
              "assets/images/resized/0026/8869/268869v2-max-150x150.jpg"],
             [[250,
               19],
              "assets/images/resized/0026/8869/268869v2-max-250x250.jpg"],
             [[450,
               35],
              "assets/images/resized/0026/8869/268869v2-max-450x450.jpg"]],
           "attribution": null}},
       "person": null},
      {"company":
        {"name": "Biedermann Motech",
         "permalink": "biedermann-motech",
         "image":
          {"available_sizes":
            [[[147,
               150],
              "assets/images/resized/0019/6790/196790v1-max-150x150.jpg"],
             [[151,
               154],
              "assets/images/resized/0019/6790/196790v1-max-250x250.jpg"],
             [[151,
               154],
              "assets/images/resized/0019/6790/196790v1-max-450x450.jpg"]],
           "attribution": null}},
       "financial_org": null,
       "person": null}]}],
 "investments":
  [],
 "acquisition": null,
 "acquisitions":
  [],
 "offices":
  [{"description": "",
    "address1": "290 Utah Avenue, Suite 200",
    "address2": "",
    "zip_code": "94080",
    "city": "South San Francisco",
    "state_code": "CA",
    "country_code": "USA",
    "latitude": null,
    "longitude": null}],
 "milestones":
  [],
 "ipo": null,
 "video_embeds":
  [],
 "screenshots":
  [{"available_sizes":
     [[[150,
        107],
       "assets/images/resized/0019/6789/196789v1-max-150x150.jpg"],
      [[250,
        179],
       "assets/images/resized/0019/6789/196789v1-max-250x250.jpg"],
      [[450,
        322],
       "assets/images/resized/0019/6789/196789v1-max-450x450.jpg"]],
    "attribution": null}],
 "external_links":
  []}