{"name": "Coca-Cola Company",
 "permalink": "coca-cola-company",
 "crunchbase_url": "http://www.crunchbase.com/company/coca-cola-company",
 "homepage_url": null,
 "blog_url": null,
 "blog_feed_url": null,
 "twitter_username": null,
 "category_code": null,
 "number_of_employees": null,
 "founded_year": null,
 "founded_month": null,
 "founded_day": null,
 "deadpooled_year": null,
 "deadpooled_month": null,
 "deadpooled_day": null,
 "deadpooled_url": null,
 "tag_list": null,
 "alias_list": null,
 "email_address": null,
 "phone_number": null,
 "description": null,
 "created_at": "Sat May 18 16:20:42 UTC 2013",
 "updated_at": "Sat May 18 16:20:42 UTC 2013",
 "overview": null,
 "image": null,
 "products":
  [],
 "relationships":
  [{"is_past": false,
    "title": "",
    "person":
     {"first_name": "GORDON",
      "last_name": "PENNINGTON",
      "permalink": "gordon-pennington",
      "image": null}},
   {"is_past": true,
    "title": "National Manager - Costing \u0026 Special Projects",
    "person":
     {"first_name": "Raman",
      "last_name": "Garg",
      "permalink": "raman-garg",
      "image":
       {"available_sizes":
         [[[130,
            130],
           "assets/images/resized/0026/8618/268618v1-max-150x150.jpg"],
          [[130,
            130],
           "assets/images/resized/0026/8618/268618v1-max-250x250.jpg"],
          [[130,
            130],
           "assets/images/resized/0026/8618/268618v1-max-450x450.jpg"]],
        "attribution": ""}}},
   {"is_past": true,
    "title": "Area General Manager",
    "person":
     {"first_name": "Samyukth",
      "last_name": "Sridharan",
      "permalink": "samyukth-sridharan",
      "image":
       {"available_sizes":
         [[[150,
            150],
           "assets/images/resized/0027/0855/270855v1-max-150x150.jpg"],
          [[200,
            200],
           "assets/images/resized/0027/0855/270855v1-max-250x250.jpg"],
          [[200,
            200],
           "assets/images/resized/0027/0855/270855v1-max-450x450.jpg"]],
        "attribution": ""}}}],
 "competitions":
  [],
 "providerships":
  [],
 "total_money_raised": "$0",
 "funding_rounds":
  [],
 "investments":
  [],
 "acquisition": null,
 "acquisitions":
  [],
 "offices":
  [],
 "milestones":
  [],
 "ipo": null,
 "video_embeds":
  [],
 "screenshots":
  [],
 "external_links":
  []}