{"name": "Dailysteals",
 "permalink": "dailysteals",
 "crunchbase_url": "http://www.crunchbase.com/company/dailysteals",
 "homepage_url": "http://www.dailysteals.com",
 "blog_url": "http://www.dailystealsblog.com/",
 "blog_feed_url": "",
 "twitter_username": "dailysteals",
 "category_code": "web",
 "number_of_employees": 35,
 "founded_year": 2008,
 "founded_month": 7,
 "founded_day": null,
 "deadpooled_year": null,
 "deadpooled_month": null,
 "deadpooled_day": null,
 "deadpooled_url": null,
 "tag_list": "consumer-electronics, home, luxury, jewelry, toys, mobile, daily-deal, deals, bargains, e-commerce",
 "alias_list": null,
 "email_address": "sales@dailysteals.com",
 "phone_number": "888-50-DAILY ",
 "description": "Daily Deal Website",
 "created_at": "Wed May 18 20:24:26 UTC 2011",
 "updated_at": "Fri Mar 22 15:20:38 UTC 2013",
 "overview": "\u003Cp\u003EDailysteals.com was founded in 2008 by Matt Wiener, the idea coming from the wholesale electronics business he was running since 2006. It began with a single employee in a small bedroom and has grown to become one of the largest daily deal sites in the country, now operating out of a 12,000 sq. foot warehouse that holds 35 employees in addition to the thousands of products shipping out each day.\u003C/p\u003E\n\n\u003Cp\u003EFollowing the daily deal concept, new products are available for purchase at midnight and last for 24 hours or until sold out. Items are featured at an average price of 70%-90% off.\u003C/p\u003E\n\n\u003Cp\u003EDailysteals places their focus on both low prices and customer experience. They strive to provide quality customer care and entertainment through their own site and through social media. Within the daily deal industry, Dailysteals was one of the first to implement phone support and online live chat. A weekly raffle includes prizes such as the Apple iPad, the Sony PlayStation 3 and a Vizio HDTV, always presented by a video created in-house. In addition to the raffle, prizes are given out regularly via Facebook in the form of interactive contests.\u003C/p\u003E\n\n\u003Cp\u003EWith the support of repeat customers, Dailysteals is growing continuously and has expanded their offering from a single site to include Mobile, Home, Luxury and Toy sites. They view the daily deal site as a successful stepping stone to other innovations and projects they plan to launch in the e-commerce field. \u003C/p\u003E\n\n\u003Cp\u003EThe Dailysteals mission is not only to offer spectacular deals but also create an amazing buying experience for its customers. \u003C/p\u003E",
 "image":
  {"available_sizes":
    [[[131,
       150],
      "assets/images/resized/0013/9549/139549v2-max-150x150.jpg"],
     [[219,
       250],
      "assets/images/resized/0013/9549/139549v2-max-250x250.jpg"],
     [[394,
       450],
      "assets/images/resized/0013/9549/139549v2-max-450x450.jpg"]],
   "attribution": null},
 "products":
  [],
 "relationships":
  [{"is_past": false,
    "title": "CEO / Founder",
    "person":
     {"first_name": "Matt",
      "last_name": "Wiener",
      "permalink": "matt-wiener",
      "image": null}},
   {"is_past": false,
    "title": "Vice President",
    "person":
     {"first_name": "Ben",
      "last_name": "Cousin",
      "permalink": "ben-cousin",
      "image": null}},
   {"is_past": false,
    "title": "Executive Buyer",
    "person":
     {"first_name": "Mendy",
      "last_name": "Nachlas",
      "permalink": "mendy-nachlas",
      "image": null}},
   {"is_past": false,
    "title": "Marketplace Manager",
    "person":
     {"first_name": "Sruli",
      "last_name": "Creeger",
      "permalink": "sruli-creeger",
      "image": null}},
   {"is_past": false,
    "title": "Business Development",
    "person":
     {"first_name": "Greg",
      "last_name": "Grinman",
      "permalink": "greg-grinman",
      "image": null}}],
 "competitions":
  [{"competitor":
     {"name": "1SaleADay LLC",
      "permalink": "1saleaday",
      "image":
       {"available_sizes":
         [[[150,
            72],
           "assets/images/resized/0006/0481/60481v5-max-150x150.jpg"],
          [[210,
            101],
           "assets/images/resized/0006/0481/60481v5-max-250x250.jpg"],
          [[210,
            101],
           "assets/images/resized/0006/0481/60481v5-max-450x450.jpg"]],
        "attribution": null}}},
   {"competitor":
     {"name": "Yugster",
      "permalink": "yugster",
      "image": null}},
   {"competitor":
     {"name": "Tanga",
      "permalink": "tanga",
      "image":
       {"available_sizes":
         [[[129,
            58],
           "assets/images/resized/0011/2793/112793v2-max-150x150.png"],
          [[129,
            58],
           "assets/images/resized/0011/2793/112793v2-max-250x250.png"],
          [[129,
            58],
           "assets/images/resized/0011/2793/112793v2-max-450x450.png"]],
        "attribution": null}}},
   {"competitor":
     {"name": "Woot",
      "permalink": "woot",
      "image":
       {"available_sizes":
         [[[150,
            146],
           "assets/images/resized/0000/3124/3124v1-max-150x150.png"],
          [[250,
            243],
           "assets/images/resized/0000/3124/3124v1-max-250x250.png"],
          [[450,
            438],
           "assets/images/resized/0000/3124/3124v1-max-450x450.png"]],
        "attribution": null}}},
   {"competitor":
     {"name": "JomaDeals",
      "permalink": "jomadeals-com",
      "image":
       {"available_sizes":
         [[[150,
            49],
           "assets/images/resized/0006/4632/64632v2-max-150x150.jpg"],
          [[250,
            81],
           "assets/images/resized/0006/4632/64632v2-max-250x250.jpg"],
          [[303,
            99],
           "assets/images/resized/0006/4632/64632v2-max-450x450.jpg"]],
        "attribution": null}}},
   {"competitor":
     {"name": "ideeli",
      "permalink": "ideeli",
      "image":
       {"available_sizes":
         [[[150,
            58],
           "assets/images/resized/0000/2701/2701v5-max-150x150.jpg"],
          [[226,
            88],
           "assets/images/resized/0000/2701/2701v5-max-250x250.jpg"],
          [[226,
            88],
           "assets/images/resized/0000/2701/2701v5-max-450x450.jpg"]],
        "attribution": null}}},
   {"competitor":
     {"name": "Laalo.com",
      "permalink": "laalo-com",
      "image":
       {"available_sizes":
         [[[150,
            80],
           "assets/images/resized/0013/0448/130448v2-max-150x150.png"],
          [[250,
            134],
           "assets/images/resized/0013/0448/130448v2-max-250x250.png"],
          [[401,
            216],
           "assets/images/resized/0013/0448/130448v2-max-450x450.png"]],
        "attribution": null}}}],
 "providerships":
  [],
 "total_money_raised": "$0",
 "funding_rounds":
  [],
 "investments":
  [],
 "acquisition": null,
 "acquisitions":
  [],
 "offices":
  [{"description": "NYC",
    "address1": "1529 Dean St #3",
    "address2": "",
    "zip_code": "11213",
    "city": "Brooklyn",
    "state_code": "NY",
    "country_code": "USA",
    "latitude": null,
    "longitude": null}],
 "milestones":
  [],
 "ipo": null,
 "video_embeds":
  [],
 "screenshots":
  [{"available_sizes":
     [[[150,
        129],
       "assets/images/resized/0013/5238/135238v2-max-150x150.jpg"],
      [[250,
        215],
       "assets/images/resized/0013/5238/135238v2-max-250x250.jpg"],
      [[450,
        388],
       "assets/images/resized/0013/5238/135238v2-max-450x450.jpg"]],
    "attribution": null},
   {"available_sizes":
     [[[150,
        136],
       "assets/images/resized/0013/5239/135239v2-max-150x150.jpg"],
      [[250,
        227],
       "assets/images/resized/0013/5239/135239v2-max-250x250.jpg"],
      [[450,
        409],
       "assets/images/resized/0013/5239/135239v2-max-450x450.jpg"]],
    "attribution": null},
   {"available_sizes":
     [[[150,
        124],
       "assets/images/resized/0013/5240/135240v2-max-150x150.jpg"],
      [[250,
        207],
       "assets/images/resized/0013/5240/135240v2-max-250x250.jpg"],
      [[450,
        373],
       "assets/images/resized/0013/5240/135240v2-max-450x450.jpg"]],
    "attribution": null},
   {"available_sizes":
     [[[150,
        125],
       "assets/images/resized/0013/5241/135241v2-max-150x150.jpg"],
      [[250,
        209],
       "assets/images/resized/0013/5241/135241v2-max-250x250.jpg"],
      [[450,
        376],
       "assets/images/resized/0013/5241/135241v2-max-450x450.jpg"]],
    "attribution": null},
   {"available_sizes":
     [[[150,
        112],
       "assets/images/resized/0013/5242/135242v2-max-150x150.jpg"],
      [[250,
        186],
       "assets/images/resized/0013/5242/135242v2-max-250x250.jpg"],
      [[450,
        336],
       "assets/images/resized/0013/5242/135242v2-max-450x450.jpg"]],
    "attribution": null}],
 "external_links":
  []}