{"name": "eMobc",
 "permalink": "emobc",
 "crunchbase_url": "http://www.crunchbase.com/company/emobc",
 "homepage_url": "http://www.emobc.com",
 "blog_url": "http://blog.emobc.com",
 "blog_feed_url": "",
 "twitter_username": "emobcapp",
 "category_code": "software",
 "number_of_employees": 15,
 "founded_year": 2013,
 "founded_month": 1,
 "founded_day": 1,
 "deadpooled_year": null,
 "deadpooled_month": null,
 "deadpooled_day": null,
 "deadpooled_url": null,
 "tag_list": "mobile, apps, framework",
 "alias_list": null,
 "email_address": "contacto@emobc.com",
 "phone_number": "(+34) 916 851 242",
 "description": "Mobile Application Framework",
 "created_at": "Sun May 19 14:55:10 UTC 2013",
 "updated_at": "Thu May 23 18:06:51 UTC 2013",
 "overview": "\u003Cp\u003EeMobc is a mobile framework to develop mobile applications, webapps and webmobile using XML. Supported native platforms are IOS, Android and HTML5, each developed in their own language (Java, Obj-C and PHP).\u003C/p\u003E\n\n\u003Cp\u003EeMobc has a cloud service to develop mobile landing pages and websites.\u003C/p\u003E",
 "image":
  {"available_sizes":
    [[[150,
       38],
      "assets/images/resized/0026/4123/264123v2-max-150x150.png"],
     [[250,
       63],
      "assets/images/resized/0026/4123/264123v2-max-250x250.png"],
     [[327,
       83],
      "assets/images/resized/0026/4123/264123v2-max-450x450.png"]],
   "attribution": null},
 "products":
  [{"name": "eMobc Framework",
    "permalink": "emobc-framework",
    "image": null},
   {"name": "eMobc Lander Cloud",
    "permalink": "emobc-lander-cloud",
    "image": null}],
 "relationships":
  [],
 "competitions":
  [],
 "providerships":
  [],
 "total_money_raised": "$0",
 "funding_rounds":
  [],
 "investments":
  [],
 "acquisition": null,
 "acquisitions":
  [],
 "offices":
  [{"description": "Madrid",
    "address1": "",
    "address2": "",
    "zip_code": "",
    "city": "Madrid",
    "state_code": null,
    "country_code": "ESP",
    "latitude": null,
    "longitude": null}],
 "milestones":
  [],
 "ipo": null,
 "video_embeds":
  [{"embed_code": "\u003Ciframe width=\"560\" height=\"315\" src=\"http://www.youtube.com/embed/VSJiVG-KkBk\" frameborder=\"0\" allowfullscreen\u003E\u003C/iframe\u003E",
    "description": "\u003Cp\u003EeMobc\u003C/p\u003E"}],
 "screenshots":
  [],
 "external_links":
  [{"external_url": "http://www.emobc.com",
    "title": "eMobc"},
   {"external_url": "http://www.emobcloud.com",
    "title": "Cloud"}]}