{"name": "JobVidi",
 "permalink": "jobvidi",
 "crunchbase_url": "http://www.crunchbase.com/company/jobvidi",
 "homepage_url": "http://www.jobvidi.com",
 "blog_url": "",
 "blog_feed_url": "",
 "twitter_username": "JobVidi",
 "category_code": "other",
 "number_of_employees": 3,
 "founded_year": 2012,
 "founded_month": 2,
 "founded_day": 10,
 "deadpooled_year": null,
 "deadpooled_month": null,
 "deadpooled_day": null,
 "deadpooled_url": null,
 "tag_list": "social-media, recruitment",
 "alias_list": null,
 "email_address": "info@jobvidi.com",
 "phone_number": "",
 "description": "Social media recruitment",
 "created_at": "Fri Jul 06 13:42:56 UTC 2012",
 "updated_at": "Mon Jul 09 18:44:38 UTC 2012",
 "overview": "\u003Cp\u003EJobVidi makes the job-seeking process a more efficient, interactive and discreet experience for candidates by utilising social networks.\u003C/p\u003E",
 "image":
  {"available_sizes":
    [[[89,
       86],
      "assets/images/resized/0019/9231/199231v2-max-150x150.png"],
     [[89,
       86],
      "assets/images/resized/0019/9231/199231v2-max-250x250.png"],
     [[89,
       86],
      "assets/images/resized/0019/9231/199231v2-max-450x450.png"]],
   "attribution": null},
 "products":
  [],
 "relationships":
  [],
 "competitions":
  [],
 "providerships":
  [],
 "total_money_raised": "$0",
 "funding_rounds":
  [],
 "investments":
  [],
 "acquisition": null,
 "acquisitions":
  [],
 "offices":
  [],
 "milestones":
  [],
 "ipo": null,
 "video_embeds":
  [],
 "screenshots":
  [],
 "external_links":
  []}