{"name": "Kolectiv Studio",
 "permalink": "kolectiv-studio",
 "crunchbase_url": "http://www.crunchbase.com/company/kolectiv-studio",
 "homepage_url": "http://www.kolectivstudio.com/",
 "blog_url": "",
 "blog_feed_url": "",
 "twitter_username": "",
 "category_code": "software",
 "number_of_employees": 10,
 "founded_year": 2001,
 "founded_month": null,
 "founded_day": null,
 "deadpooled_year": null,
 "deadpooled_month": null,
 "deadpooled_day": null,
 "deadpooled_url": null,
 "tag_list": "mobile-app-development, iphone-development, android-development, windows-mobile-development, smartphone-development, app-development, apps-developer, mobile-development, web-development, responsive-design, android-app, iphone-app, ipad-app, ios, software-",
 "alias_list": null,
 "email_address": "contact@kolectivstudio.com",
 "phone_number": "",
 "description": "mobile app and website development",
 "created_at": "Fri Mar 29 10:59:18 UTC 2013",
 "updated_at": "Thu Apr 04 09:57:36 UTC 2013",
 "overview": "\u003Cp\u003EKolectiv Studio is a team of programmers that think outside the code box. With over 12 years experience in web developing and design, the company creates valuable interactive experiences for customers, business partners and colleagues.\u003C/p\u003E\n\n\u003Cp\u003EThe company started in Europe, Romania and grew project by project having now an office in Germany and numerous collaborations with the U.S. market.\u003C/p\u003E\n\n\u003Cp\u003EOffering full-service development, the company covers a series of services, starting with web, software, design, iOS, Android, e-commerce and social media.\u003C/p\u003E\n\n\u003Cp\u003EIn a nutshell, Kolectiv Studio is a team of professionals that makes products useful both to the client\u0026#8217;s business and to the user\u0026#8217;s experience.\u003C/p\u003E",
 "image":
  {"available_sizes":
    [[[150,
       24],
      "assets/images/resized/0024/6504/246504v2-max-150x150.png"],
     [[218,
       35],
      "assets/images/resized/0024/6504/246504v2-max-250x250.png"],
     [[218,
       35],
      "assets/images/resized/0024/6504/246504v2-max-450x450.png"]],
   "attribution": null},
 "products":
  [],
 "relationships":
  [{"is_past": false,
    "title": "Founder",
    "person":
     {"first_name": "Paul",
      "last_name": "Vlad",
      "permalink": "paul-vlad",
      "image":
       {"available_sizes":
         [[[150,
            150],
           "assets/images/resized/0024/6988/246988v2-max-150x150.jpg"],
          [[250,
            250],
           "assets/images/resized/0024/6988/246988v2-max-250x250.jpg"],
          [[450,
            450],
           "assets/images/resized/0024/6988/246988v2-max-450x450.jpg"]],
        "attribution": "\u003Cp\u003EPaul Vlad / \u003Ca href=\"http://www.kolectivstudio.com\" title=\"Kolectiv Studio\" rel=\"nofollow\"\u003EKolectiv Studio\u003C/a\u003E\u003C/p\u003E"}}}],
 "competitions":
  [],
 "providerships":
  [],
 "total_money_raised": "$0",
 "funding_rounds":
  [],
 "investments":
  [],
 "acquisition": null,
 "acquisitions":
  [],
 "offices":
  [{"description": "Bucharest Headquarters",
    "address1": "1 Popa Tatu Street",
    "address2": "",
    "zip_code": "010801",
    "city": "Bucharest",
    "state_code": null,
    "country_code": "ROM",
    "latitude": null,
    "longitude": null}],
 "milestones":
  [],
 "ipo": null,
 "video_embeds":
  [],
 "screenshots":
  [{"available_sizes":
     [[[150,
        63],
       "assets/images/resized/0024/7744/247744v2-max-150x150.png"],
      [[250,
        105],
       "assets/images/resized/0024/7744/247744v2-max-250x250.png"],
      [[450,
        190],
       "assets/images/resized/0024/7744/247744v2-max-450x450.png"]],
    "attribution": null},
   {"available_sizes":
     [[[150,
        63],
       "assets/images/resized/0024/7748/247748v2-max-150x150.png"],
      [[250,
        105],
       "assets/images/resized/0024/7748/247748v2-max-250x250.png"],
      [[450,
        190],
       "assets/images/resized/0024/7748/247748v2-max-450x450.png"]],
    "attribution": null},
   {"available_sizes":
     [[[150,
        63],
       "assets/images/resized/0024/7765/247765v2-max-150x150.png"],
      [[250,
        105],
       "assets/images/resized/0024/7765/247765v2-max-250x250.png"],
      [[450,
        189],
       "assets/images/resized/0024/7765/247765v2-max-450x450.png"]],
    "attribution": null},
   {"available_sizes":
     [[[150,
        63],
       "assets/images/resized/0024/7780/247780v2-max-150x150.png"],
      [[250,
        105],
       "assets/images/resized/0024/7780/247780v2-max-250x250.png"],
      [[450,
        190],
       "assets/images/resized/0024/7780/247780v2-max-450x450.png"]],
    "attribution": null}],
 "external_links":
  [{"external_url": "http://www.kolectivstudio.com/",
    "title": "View company"}]}