{"name": "Lagotek",
 "permalink": "lagotek",
 "crunchbase_url": "http://www.crunchbase.com/company/lagotek",
 "homepage_url": "http://www.lagotek.com/",
 "blog_url": "",
 "blog_feed_url": "",
 "twitter_username": "",
 "category_code": "hardware",
 "number_of_employees": null,
 "founded_year": 2005,
 "founded_month": null,
 "founded_day": null,
 "deadpooled_year": null,
 "deadpooled_month": null,
 "deadpooled_day": null,
 "deadpooled_url": null,
 "tag_list": "",
 "alias_list": "",
 "email_address": "info@lagotek.com",
 "phone_number": "+1 (425) 455-2165",
 "description": "Wireless Home Automation",
 "created_at": "Wed Jan 06 18:16:50 UTC 2010",
 "updated_at": "Mon Feb 08 21:51:21 UTC 2010",
 "overview": "\u003Cp\u003ELagotek Corporation is a privately held company that specializes in residential technology systems. Formed in June 2005, Lagotek builds its approach to home automation via software solutions running on an \u0026#8220;open hardware platform.\u0026#8221; \u003C/p\u003E\n\n\u003Cp\u003ELagotek also developed the Home Intelligence Platform (HIP) technology. HIP is a \u0026#8220;wireless home automation system that allows homeowners a complete control of lighting, temperature, entertainment, surveillance, security, irrigation and other home appliances in any room from any location of their home.\u0026#8221;\u003C/p\u003E",
 "image":
  {"available_sizes":
    [[[150,
       61],
      "assets/images/resized/0007/2399/72399v1-max-150x150.png"],
     [[161,
       66],
      "assets/images/resized/0007/2399/72399v1-max-250x250.png"],
     [[161,
       66],
      "assets/images/resized/0007/2399/72399v1-max-450x450.png"]],
   "attribution": null},
 "products":
  [],
 "relationships":
  [{"is_past": false,
    "title": "Director",
    "person":
     {"first_name": "Jack",
      "last_name": "Tenhulzen",
      "permalink": "jack-tenhulzen",
      "image": null}},
   {"is_past": false,
    "title": "Director",
    "person":
     {"first_name": "Gregory",
      "last_name": "Palant",
      "permalink": "gregory-palant",
      "image": null}}],
 "competitions":
  [],
 "providerships":
  [],
 "total_money_raised": "$5.06M",
 "funding_rounds":
  [{"round_code": "b",
    "source_url": "http://www.sec.gov/Archives/edgar/data/1334058/000133405810000002/xslFormDX01/primary_doc.xml",
    "source_description": "SEC D",
    "raised_amount": 5063236.0,
    "raised_currency_code": "USD",
    "funded_year": 2010,
    "funded_month": 1,
    "funded_day": 6,
    "investments":
     []}],
 "investments":
  [],
 "acquisition": null,
 "acquisitions":
  [],
 "offices":
  [{"description": "",
    "address1": "11661 S.E. 1st Street",
    "address2": "Suite 208",
    "zip_code": "98005",
    "city": "Bellevue",
    "state_code": "WA",
    "country_code": "USA",
    "latitude": null,
    "longitude": null}],
 "milestones":
  [],
 "ipo": null,
 "video_embeds":
  [],
 "screenshots":
  [{"available_sizes":
     [[[150,
        91],
       "assets/images/resized/0007/6376/76376v1-max-150x150.jpg"],
      [[250,
        152],
       "assets/images/resized/0007/6376/76376v1-max-250x250.jpg"],
      [[450,
        275],
       "assets/images/resized/0007/6376/76376v1-max-450x450.jpg"]],
    "attribution": null}],
 "external_links":
  []}