{"name": "PAUL Secret",
 "permalink": "paul-secret",
 "crunchbase_url": "http://www.crunchbase.com/company/paul-secret",
 "homepage_url": "http://www.outfittery.de",
 "blog_url": "http://blog.outfittery.de/",
 "blog_feed_url": "",
 "twitter_username": "",
 "category_code": null,
 "number_of_employees": null,
 "founded_year": 2012,
 "founded_month": 1,
 "founded_day": 1,
 "deadpooled_year": null,
 "deadpooled_month": null,
 "deadpooled_day": null,
 "deadpooled_url": null,
 "tag_list": "",
 "alias_list": "",
 "email_address": "service@outfittery.de",
 "phone_number": "0178 7325343",
 "description": "",
 "created_at": "Thu Jun 14 03:28:25 UTC 2012",
 "updated_at": "Tue Jul 03 16:52:24 UTC 2012",
 "overview": "\u003Cp\u003EPAUL SECRET is a service for all men who would rather spend their time doing something else, as a fashion shop.\u003C/p\u003E",
 "image":
  {"available_sizes":
    [[[150,
       32],
      "assets/images/resized/0019/5414/195414v1-max-150x150.jpg"],
     [[250,
       53],
      "assets/images/resized/0019/5414/195414v1-max-250x250.jpg"],
     [[295,
       63],
      "assets/images/resized/0019/5414/195414v1-max-450x450.jpg"]],
   "attribution": null},
 "products":
  [],
 "relationships":
  [],
 "competitions":
  [],
 "providerships":
  [],
 "total_money_raised": "$0",
 "funding_rounds":
  [{"round_code": "unattributed",
    "source_url": "http://www.finsmes.com/2012/06/paul-secret-raises-funding.html?utm_source=feedburner\u0026utm_medium=feed\u0026utm_campaign=Feed%3A+finsmes%2FcNHu+%28FinSMEs%29",
    "source_description": "PAUL SECRET Raises Funding",
    "raised_amount": null,
    "raised_currency_code": null,
    "funded_year": 2012,
    "funded_month": 6,
    "funded_day": 13,
    "investments":
     [{"company": null,
       "financial_org":
        {"name": "HV Holtzbrinck Ventures",
         "permalink": "holtzbrinck-ventures",
         "image":
          {"available_sizes":
            [[[150,
               30],
              "assets/images/resized/0001/8480/18480v3-max-150x150.jpg"],
             [[250,
               51],
              "assets/images/resized/0001/8480/18480v3-max-250x250.jpg"],
             [[450,
               92],
              "assets/images/resized/0001/8480/18480v3-max-450x450.jpg"]],
           "attribution": null}},
       "person": null},
      {"company": null,
       "financial_org":
        {"name": "High-Tech Gruenderfonds",
         "permalink": "high-tech-gruenderfonds",
         "image":
          {"available_sizes":
            [[[150,
               41],
              "assets/images/resized/0002/8109/28109v4-max-150x150.jpg"],
             [[250,
               69],
              "assets/images/resized/0002/8109/28109v4-max-250x250.jpg"],
             [[450,
               125],
              "assets/images/resized/0002/8109/28109v4-max-450x450.jpg"]],
           "attribution": null}},
       "person": null}]}],
 "investments":
  [],
 "acquisition": null,
 "acquisitions":
  [],
 "offices":
  [{"description": "",
    "address1": "6-7 Sch\u00f6nhauser Allee",
    "address2": "",
    "zip_code": "10119",
    "city": "Berlin",
    "state_code": null,
    "country_code": "DEU",
    "latitude": null,
    "longitude": null}],
 "milestones":
  [],
 "ipo": null,
 "video_embeds":
  [],
 "screenshots":
  [{"available_sizes":
     [[[150,
        112],
       "assets/images/resized/0019/5415/195415v1-max-150x150.jpg"],
      [[250,
        188],
       "assets/images/resized/0019/5415/195415v1-max-250x250.jpg"],
      [[450,
        338],
       "assets/images/resized/0019/5415/195415v1-max-450x450.jpg"]],
    "attribution": null}],
 "external_links":
  []}