{"name": "Watson Voice",
 "permalink": "watson-voice",
 "crunchbase_url": "http://www.crunchbase.com/company/watson-voice",
 "homepage_url": "http://www.watsonvoice.com",
 "blog_url": "",
 "blog_feed_url": "",
 "twitter_username": "WatsonVoice",
 "category_code": "public_relations",
 "number_of_employees": 10,
 "founded_year": 2012,
 "founded_month": 11,
 "founded_day": null,
 "deadpooled_year": null,
 "deadpooled_month": null,
 "deadpooled_day": null,
 "deadpooled_url": null,
 "tag_list": "",
 "alias_list": null,
 "email_address": "sales@watsonvoice.com",
 "phone_number": "334-212-8000",
 "description": "Custom Tailored Communications",
 "created_at": "Thu Jun 06 23:25:15 UTC 2013",
 "updated_at": "Fri Jun 07 21:47:16 UTC 2013",
 "overview": "",
 "image":
  {"available_sizes":
    [[[150,
       66],
      "assets/images/resized/0027/2489/272489v2-max-150x150.png"],
     [[250,
       111],
      "assets/images/resized/0027/2489/272489v2-max-250x250.png"],
     [[400,
       178],
      "assets/images/resized/0027/2489/272489v2-max-450x450.png"]],
   "attribution": null},
 "products":
  [],
 "relationships":
  [{"is_past": false,
    "title": "Founder / CEO",
    "person":
     {"first_name": "Justin",
      "last_name": "B. Watson",
      "permalink": "justin-b-watson",
      "image": null}},
   {"is_past": false,
    "title": "VP",
    "person":
     {"first_name": "Kirk",
      "last_name": "L. Anderson",
      "permalink": "kirk-l-anderson",
      "image": null}},
   {"is_past": false,
    "title": "VP",
    "person":
     {"first_name": "Dave",
      "last_name": "Turnbull",
      "permalink": "dave-turnbull",
      "image": null}}],
 "competitions":
  [],
 "providerships":
  [],
 "total_money_raised": "$0",
 "funding_rounds":
  [],
 "investments":
  [],
 "acquisition": null,
 "acquisitions":
  [],
 "offices":
  [{"description": "Corporate Offices",
    "address1": "2078 Highway 14 East",
    "address2": "",
    "zip_code": "36066",
    "city": "Prattville",
    "state_code": "AL",
    "country_code": "USA",
    "latitude": 32.4858638,
    "longitude": -86.4115885}],
 "milestones":
  [],
 "ipo": null,
 "video_embeds":
  [],
 "screenshots":
  [],
 "external_links":
  []}