{"name": "Weather Underground",
 "permalink": "weather-underground",
 "crunchbase_url": "http://www.crunchbase.com/company/weather-underground",
 "homepage_url": "http://wunderground.com",
 "blog_url": "",
 "blog_feed_url": "",
 "twitter_username": "WeatherAPI",
 "category_code": "other",
 "number_of_employees": 60,
 "founded_year": 1994,
 "founded_month": null,
 "founded_day": null,
 "deadpooled_year": null,
 "deadpooled_month": null,
 "deadpooled_day": null,
 "deadpooled_url": null,
 "tag_list": "weather, weather-data, weather-forecast, weather-api, weather-radar, hurricane-map, hurricane, tornado, historical-weather-information, forecasts, hurricane-tracking",
 "alias_list": null,
 "email_address": "",
 "phone_number": "415.543.5022",
 "description": "World's First Weather Website",
 "created_at": "Mon Aug 22 23:21:31 UTC 2011",
 "updated_at": "Tue Jul 03 03:15:24 UTC 2012",
 "overview": "\u003Cp\u003EWeather Underground is committed to delivering the most reliable, accurate weather information possible. \u003C/p\u003E\n\n\u003Cp\u003EWunderground.com\u0026#8217;s  state-of-the-art technology monitors conditions and forecasts for locations across the world, so you\u0026#8217;ll always find the weather information that you need.  In addition to providing free, real-time online weather information to millions of Web users around the world, Weather Underground also streams live weather data to thousands of news and media outlets around the world.  \u003C/p\u003E",
 "image":
  {"available_sizes":
    [[[150,
       110],
      "assets/images/resized/0015/0603/150603v2-max-150x150.png"],
     [[250,
       184],
      "assets/images/resized/0015/0603/150603v2-max-250x250.png"],
     [[450,
       332],
      "assets/images/resized/0015/0603/150603v2-max-450x450.png"]],
   "attribution": null},
 "products":
  [],
 "relationships":
  [],
 "competitions":
  [],
 "providerships":
  [],
 "total_money_raised": "$0",
 "funding_rounds":
  [],
 "investments":
  [],
 "acquisition":
  {"price_amount": null,
   "price_currency_code": "USD",
   "term_code": null,
   "source_url": "http://techcrunch.com/2012/07/02/nice-move-weather-channel-buys-weather-underground-to-sharpen-focus-on-digital/",
   "source_description": "The Weather Channel Buys Weather Underground To Sharpen Focus On Digital",
   "acquired_year": 2012,
   "acquired_month": 7,
   "acquired_day": 2,
   "acquiring_company":
    {"name": "The Weather Channel",
     "permalink": "the-weather-channel",
     "image":
      {"available_sizes":
        [[[71,
           60],
          "assets/images/resized/0002/1543/21543v1-max-150x150.png"],
         [[71,
           60],
          "assets/images/resized/0002/1543/21543v1-max-250x250.png"],
         [[71,
           60],
          "assets/images/resized/0002/1543/21543v1-max-450x450.png"]],
       "attribution": null}}},
 "acquisitions":
  [],
 "offices":
  [],
 "milestones":
  [],
 "ipo": null,
 "video_embeds":
  [],
 "screenshots":
  [],
 "external_links":
  []}